xtictoc/__init__.py
xtictoc/__main__.py
xtictoc/bot.py
xtictoc/game.py
xtictoc-1.0.2.dist-info/entry_points.txt
xtictoc-1.0.2.dist-info/METADATA
xtictoc-1.0.2.dist-info/WHEEL
xtictoc-1.0.2.dist-info/RECORD
