Metadata-Version: 2.1
Name: xtictoc
Version: 1.0.2
Summary: Welcome to Xtictoc, a simple console-based Tic-Tac-Toe (XO) game in Python.
Author: Wation
Requires-Python: >=3.6,<4.0
Classifier: Programming Language :: Python :: 3
Classifier: Programming Language :: Python :: 3.6
Classifier: Programming Language :: Python :: 3.7
Classifier: Programming Language :: Python :: 3.8
Classifier: Programming Language :: Python :: 3.9
Classifier: Programming Language :: Python :: 3.10
Classifier: Programming Language :: Python :: 3.11
Classifier: Programming Language :: Python :: 3.12
